{
  "$schema": "https://raw.githubusercontent.com/spdx/spdx-spec/v2.2.1/schemas/spdx-schema.json",
  "spdxVersion": "SPDX-2.2",
  "dataLicense": "CC0-1.0",
  "SPDXID": "SPDXRef-DOCUMENT",
  "documentNamespace": "https://spdx.org/spdxdocs/wildmidi-x64-windows-static-0.4.5-ae3dd5a9-7076-44f5-b0be-6d140292cd0a",
  "name": "wildmidi:x64-windows-static@0.4.5 b3008815d0b298fce878afd52079fdf22dd19d99f1db87ad09d9262b6fd072d0",
  "creationInfo": {
    "creators": [
      "Tool: vcpkg-8a88d63f241d391772fbde69af9cab96c3c64c75"
    ],
    "created": "2023-02-03T02:50:45Z"
  },
  "relationships": [
    {
      "spdxElementId": "SPDXRef-port",
      "relationshipType": "GENERATES",
      "relatedSpdxElement": "SPDXRef-binary"
    },
    {
      "spdxElementId": "SPDXRef-port",
      "relationshipType": "CONTAINS",
      "relatedSpdxElement": "SPDXRef-file-0"
    },
    {
      "spdxElementId": "SPDXRef-port",
      "relationshipType": "CONTAINS",
      "relatedSpdxElement": "SPDXRef-file-1"
    },
    {
      "spdxElementId": "SPDXRef-binary",
      "relationshipType": "GENERATED_FROM",
      "relatedSpdxElement": "SPDXRef-port"
    },
    {
      "spdxElementId": "SPDXRef-file-0",
      "relationshipType": "CONTAINED_BY",
      "relatedSpdxElement": "SPDXRef-port"
    },
    {
      "spdxElementId": "SPDXRef-file-1",
      "relationshipType": "CONTAINED_BY",
      "relatedSpdxElement": "SPDXRef-port"
    },
    {
      "spdxElementId": "SPDXRef-file-1",
      "relationshipType": "DEPENDENCY_MANIFEST_OF",
      "relatedSpdxElement": "SPDXRef-port"
    }
  ],
  "packages": [
    {
      "name": "wildmidi",
      "SPDXID": "SPDXRef-port",
      "versionInfo": "0.4.5",
      "downloadLocation": "git+https://github.com/Microsoft/vcpkg#ports/wildmidi",
      "homepage": "https://github.com/Mindwerks/wildmidi",
      "licenseConcluded": "LGPL-3.0-only",
      "licenseDeclared": "NOASSERTION",
      "copyrightText": "NOASSERTION",
      "description": "MIDI software synthesizer library.",
      "comment": "This is the port (recipe) consumed by vcpkg."
    },
    {
      "name": "wildmidi:x64-windows-static",
      "SPDXID": "SPDXRef-binary",
      "versionInfo": "b3008815d0b298fce878afd52079fdf22dd19d99f1db87ad09d9262b6fd072d0",
      "downloadLocation": "NONE",
      "licenseConcluded": "LGPL-3.0-only",
      "licenseDeclared": "NOASSERTION",
      "copyrightText": "NOASSERTION",
      "comment": "This is a binary package built by vcpkg."
    },
    {
      "SPDXID": "SPDXRef-resource-1",
      "name": "Mindwerks/wildmidi",
      "downloadLocation": "git+https://github.com/Mindwerks/wildmidi@wildmidi-0.4.5",
      "licenseConcluded": "NOASSERTION",
      "licenseDeclared": "NOASSERTION",
      "copyrightText": "NOASSERTION",
      "checksums": [
        {
          "algorithm": "SHA512",
          "checksumValue": "0229914ecc60091b649b790a82ad5e755a2b9dfab7443fb3e3c19f4ae64b82817cafe74d78c27f05c68c3c8fb30092c96da732d27ff82fbd7dd7d577facc23d6"
        }
      ]
    }
  ],
  "files": [
    {
      "fileName": "./portfile.cmake",
      "SPDXID": "SPDXRef-file-0",
      "checksums": [
        {
          "algorithm": "SHA256",
          "checksumValue": "e9d608f951dc9af826b96c6706b776ee7872a8df7504b4f5f9fd6fe039dd3653"
        }
      ],
      "licenseConcluded": "NOASSERTION",
      "copyrightText": "NOASSERTION"
    },
    {
      "fileName": "./vcpkg.json",
      "SPDXID": "SPDXRef-file-1",
      "checksums": [
        {
          "algorithm": "SHA256",
          "checksumValue": "c594397a5d90b832d876c4ad152c9c86ebb78bb1c2f62877056eb6efc8617d0a"
        }
      ],
      "licenseConcluded": "NOASSERTION",
      "copyrightText": "NOASSERTION"
    }
  ]
}
